dmk/__init__.py
dmk/_cli.py
dmk/_common.py
dmk/_constants.py
dmk/_main.py
dmk/_vault_file.py
dmk/a_base/_05_codename.py
dmk/a_base/_10_kdf.py
dmk/a_base/__init__.py
dmk/a_utils/__init__.py
dmk/a_utils/bytes.py
dmk/a_utils/dirty_file.py
dmk/a_utils/randoms.py
dmk/a_utils/shred.py
dmk/b_cryptoblobs/_10_byte_funcs.py
dmk/b_cryptoblobs/_20_encdec_part.py
dmk/b_cryptoblobs/_30_encdec_multipart.py
dmk/b_cryptoblobs/__init__.py
dmk/b_storage_file/_10_fragment_io.py
dmk/b_storage_file/_20_blocks_rw.py
dmk/b_storage_file/_30_storage_file.py
dmk/b_storage_file/__init__.py
dmk/c_namegroups/__init__.py
dmk/c_namegroups/_fakes.py
dmk/c_namegroups/_namegroup.py
dmk/c_namegroups/_update.py
dmk/c_namegroups/content_ver.py
experiments/__init__.py
experiments/bench_blake_hash_sizes.py
experiments/bench_chacha_vs_blake.py
experiments/bench_get_random_bytes.py
experiments/exp.py
experiments/exp_checksum_in_encoded.py
tests/__init__.py
tests/common.py
tests/test_blob_name_group.py
tests/test_blobs_update.py
tests/test_blocks.py
tests/test_byte_funcs.py
tests/test_cli.py
tests/test_content_ver.py
tests/test_dirty_file.py
tests/test_encdec_multipart.py
tests/test_encrypt_part.py
tests/test_io_fragment.py
tests/test_kdf.py
tests/test_parse_nunits.py
tests/test_random_names.py
tests/test_randoms.py
tests/test_reference.py
tests/test_shred.py
tests/test_storage_file.py
tests/test_thefile.py
dmk-0.6.0.dist-info/LICENSE
dmk-0.6.0.dist-info/METADATA
dmk-0.6.0.dist-info/WHEEL
dmk-0.6.0.dist-info/entry_points.txt
dmk-0.6.0.dist-info/top_level.txt
dmk-0.6.0.dist-info/RECORD
