Metadata-Version: 2.1
Name: dmk
Version: 0.6.0
Summary: Experimental storage with entries encrypted independently.
Home-page: https://github.com/rtmigo/dmk_py
Author: Artëm IG
Author-email: ortemeo@gmail.com
License: MIT
Keywords: encryption,password,keeper,storage,vault,keychain,fileprivacy,deniable,data,security,chacha20,argon2
Platform: UNKNOWN
Classifier: Development Status :: 3 - Alpha
Classifier: License :: OSI Approved :: BSD License
Classifier: Programming Language :: Python :: 3.7
Classifier: Programming Language :: Python :: 3.8
Classifier: Programming Language :: Python :: 3.9
Classifier: Programming Language :: Python :: 3.10
Classifier: Topic :: Security :: Cryptography
Classifier: Environment :: Console
Classifier: Typing :: Typed
Classifier: Operating System :: POSIX
Classifier: Operating System :: Microsoft :: Windows
Requires-Python: >=3.7
License-File: LICENSE
Requires-Dist: pycryptodome
Requires-Dist: click
Requires-Dist: argon2-cffi
